{
  "corpus_root": "D:\\AVA\\corpora\\tool_memory_minimal_v1",
  "file_count": 3,
  "text_count": 25,
  "character_count": 2109,
  "token_count": 2159,
  "supervised_example_count": 24,
  "files": [
    {
      "path": "D:\\AVA\\corpora\\tool_memory_minimal_v1\\examples.jsonl",
      "size_bytes": 3089,
      "sha256": "c9f4331149ffa09ff173bf21e1de8d2cfc2c45f72f7f977fdb99da06caacfc67",
      "relative_path": "examples.jsonl"
    },
    {
      "path": "D:\\AVA\\corpora\\tool_memory_minimal_v1\\manifest.json",
      "size_bytes": 290,
      "sha256": "319021063c75716a010bc5a38fb1349f23d96a8691255e02f97963a35eee961e",
      "relative_path": "manifest.json"
    },
    {
      "path": "D:\\AVA\\corpora\\tool_memory_minimal_v1\\README.md",
      "size_bytes": 226,
      "sha256": "4ca1e65aa3752465f3b8b601e72e9bff049edef0df6299b623cb9bc5751a8120",
      "relative_path": "README.md"
    }
  ]
}